{
  "common": {
    "error": "Feil",
    "close": "Lukk",
    "error_message": "Feilmelding",
    "error_status_code": "Feilmeldingens statuskode",
    "back": "Tilbake",
    "general_error_title": "Beklager, men det har skjedd en feil",
    "general_error_paragraph": "Vi klarer ikke å hente informasjonen du ser etter akkurat nå. Vennligst prøv igjen senere. Om problemet vedvarer, ta kontakt med Altinn Servicedesk.",
    "cancel": "Avbryt",
    "choose": "Velg ..."
  },
  "authent_overviewpage": {
    "banner_title": "Administrere systemtilgang",
    "sub_title": "Lag en systemtilgang",
    "sub_title_text": "Ved å opprette en systemtilgang gir du et fagsystem tilgang til å løse oppgaver i Altinn på vegne av bedriften din.",
    "systemusers_load_error": "Kunne ikke laste systemtilganger",
    "new_system_user_button": "Lag ny systemtilgang",
    "new_first_system_user_button": "Lag systemtilgang",
    "existing_earlier_system_users_title": "Tidligere opprettede systemtilganger:",
    "existing_system_users_title": "Dine systemtilganger:",
    "created_system_user_title": "Du har nå laget denne systemtilgangen:",
    "system_user_no_rights": "Systemtilgangen inneholder ingen tjenester enda",
    "system_rights_header": "Systemtilgangen inneholder disse tjenestene:",
    "edit_system_user": "Rediger systemtilgang",
    "loading_systemusers": "Laster systemtilganger",
    "no_key_role1": "Du mangler nødvendige fullmakter.",
    "no_key_role2": "For å lage en systemtilgang trenger du rollen Tilgangsstyrer, Hovedadministrator eller Daglig leder."
  },
  "authent_creationpage": {
    "banner_title": "Lag ny systemtilgang",
    "input_field_label": "Gi systemtilgangen et navn",
    "sub_title": "Velg fagsystem",
    "content_text1": "Er du usikker på hvilket fagsystem du skal velge, anbefaler vi at du kontakter leverandøren av fagsystemet. Altinn har ikke gjort noen vurdering av kvalitet og sikkerhet på fagsystemene i listen.",
    "pull_down_menu_label": "Velg fagsystem",
    "confirm_button": "Gå videre",
    "load_vendors_error": "Kunne ikke laste systemleverandører",
    "name_too_long": "Navn på systemtilgang kan kun være 255 tegn, du har skrevet inn {{ nameLength }} tegn.",
    "loading_systems": "Laster leverandører og system..."
  },
  "authent_includedrightspage": {
    "banner_title": "Lag ny systemtilgang",
    "sub_title": "Systemtilgangen vil inneholde disse tjenestene",
    "sub_title_single": "Systemtilgangen vil inneholde denne tjenesten",
    "content_text": "Disse tjenestene er forhåndsvalgt av fagsystemet.",
    "content_text_single": "Denne tjenesten er forhåndsvalgt av fagsystemet.",
    "confirm_button": "Opprett systemtilgang",
    "create_systemuser_error": "Kunne ikke opprette systemtilgang",
    "loading_rights": "Laster forhåndsvalgte tjenester for fagsystemet",
    "load_rights_error": "Kunne ikke laste forhåndsvalgte tjenester, eller du har ikke rettigheter til å delegere alle disse tjenestene.",
    "creating_systemuser": "Oppretter systemtilgang..."
  },
  "authent_detailpage": {
    "edit_systemuser": "Rediger systemtilgang",
    "load_systemuser_error": "Kunne ikke laste systemtilgang",
    "loading_systemuser": "laster systemtilgang",
    "no_name": "<Systemtilgang uten navn>",
    "edit_systemuser_name": "Endre navn på systemtilgang",
    "delete_systemuser": "Slett systemtilgang",
    "delete_systemuser_header": "Slette systemtilgang",
    "delete_systemuser_body": "Er du sikker på at du vil slette systemtilgangen \"{{title}}\"?",
    "delete_systemuser_error": "Kunne ikke slette systemtilgang",
    "update_systemuser_error": "Kunne ikke oppdatere systemtilgang",
    "save_systemuser": "Lagre endringer",
    "name_too_long": "Navn på systemtilgang kan kun være 255 tegn, du har skrevet inn {{ nameLength }} tegn."
  },
  "error_page": {
    "go_to_inbox": "Gå til innboks",
    "go_to_profile": "Gå til profilsiden",
    "find_and_submit_scheme": "Finne og sende inn nytt skjema",
    "not_found_site_header": "Oi! Du har prøvd å komme til en side vi ikke vet om",
    "not_found_site_upper_text": "Vi vet ikke hvor du egentlig skulle, men kanskje du kan finne det du leter etter på noen av disse sidene:",
    "not_found_site_lower_text": "Hvis dette ikke var til hjelp kan du ta kontakt med Altinn brukerstøtte på telefon 75 00 60 00"
  },
  "vendor_request": {
    "banner_title": "Gi tilgang til system",
    "creation_header": "{{vendorName}} ber om godkjenning til å lage en systemtilgang",
    "system_description": "Gjennom systemtilgangen kan <strong>{{systemName}}</strong> løse oppgaver på vegne av <strong>{{partyName}}</strong>.",
    "rights_list_header": "Systemtilgangen vil inneholde disse tjenestene:",
    "rights_list_header_single": "Systemtilgangen vil inneholde denne tjenesten:",
    "withdraw_consent_info": "Du kan når som helst trekke tilbake godkjenningen og endre systemtilgangen på altinn.no.",
    "accept": "Godkjenn systemtilgang",
    "reject": "Avvis",
    "org_nr": "{{systemName}} blir levert av {{vendorName}}, org.nr. {{vendorOrg}}",
    "loading_creation_request": "Laster forespørsel",
    "load_creation_request_error_notfound": "Systemtilgang-forespørsel for valgt aktør finnes ikke. Er du sikker på at du har valgt riktig aktør?",
    "load_creation_request_error": "Kunne ikke laste systemtilgang-forespørsel",
    "load_user_info_error": "Kunne ikke laste brukerinfo",
    "load_creation_request_no_id": "id må være med som query-parameter i url",
    "accept_error": "Kunne ikke godkjenne systemtilgang",
    "reject_error": "Kunne ikke avvise systemtilgang",
    "accept_loading": "Godkjenner systemtilgang...",
    "reject_loading": "Avviser systemtilgang...",
    "request_accepted": "Denne forespørselen er allerede godkjent",
    "request_rejected": "Denne forespørselen er allerede avvist",
    "request_expired": "Denne forespørselen har utløpt",
    "receipt_header": "Systemtilgangen er klar",
    "receipt_ingress": " Du kan nå ta i bruk {{systemName}}",
    "receipt_body": "På altinn.no finner du en oversikt over systemtilgangene dine. Der kan du også endre navn på systemtilgangen, og når som helst trekke tilbake godkjenningen.",
    "receipt_close": "Lukk",
    "receipt_go_to_overview": "Se oversikt i Altinn"
  },
  "change_request": {
    "banner_title": "Oppdatering av systemtilgang",
    "change_request_header": "{{vendorName}} ber om godkjenning til å gjøre endringer i systemtilgang",
    "rights_list_header": "Etter oppdateringen vil systemtilgangen inneholde disse tjenestene:",
    "rights_list_header_single": "Etter oppdateringen vil systemtilgangen inneholde denne tjenesten:",
    "accept": "Godkjenn oppdatert systemtilgang",
    "reject": "Avvis",
    "loading_change_request": "Laster oppdaterings-forespørsel",
    "load_change_request_error": "Kunne ikke laste oppdaterings-forespørsel",
    "accept_error": "Kunne ikke godkjenne oppdatert systemtilgang",
    "reject_error": "Kunne ikke avvise oppdatert systemtilgang",
    "accept_loading": "Godkjenner oppdatert systemtilgang...",
    "reject_loading": "Avviser oppdatert systemtilgang...",
    "request_accepted": "Denne oppdaterings-forespørselen er allerede godkjent",
    "request_rejected": "Denne oppdaterings-forespørselen er allerede avvist",
    "request_expired": "Denne oppdaterings-forespørselen har utløpt"
  },
  "delegation_errors": {
    "01_rights_not_found_or_not_delegable": "En eller flere tjenester eksisterer ikke, eller er ikke delegerbare.",
    "02_rights_failed_to_delegate": "Kunne ikke delegere tjenester til systembruker.",
    "03_systemuser_failed_to_create": "Kunne ikke opprette systemtilgang.",
    "04_system_user_already_exists": "Kunne ikke opprette systemtilgang, eksisterende systemtilgang finnes allerede for valgt system.",
    "11_system_not_found": "Valgt system finnes ikke",
    "14_unable_to_do_delegation_check": "Delegering av tjenester feilet med ukjent feil.",
    "16_delegation_right_missing_role_access": "Delegering av tjenester feilet: din rolle har ikke rettigheter til å delegere tjenester til systemtilgang.",
    "18_delegation_right_missing_delegation_access": "Delegering av tjenester feilet: du har ikke rettigheter til å direkte delegere tjenester.",
    "19_delegation_right_missing_srr_right_access": "Delegering av tjenester feilet: en eller flere tjenester bruker tilgangslister der virksomhet ikke har tilgang.",
    "20_delegation_right_insufficient_authentication_level": "Delegering av tjenester feilet: en eller flere tjenester krever eksplisitt tilgangsnivå."
  }
}
